{
  "name": "Interior Designers Institute Design System",
  "version": "3.0.0",
  "theme": "rose-editorial",
  "description": "Rose color palette for IDI - a prestigious interior design school with 40 years of excellence",
  "colors": {
    "palette": {
      "heiSeBlack": "#142030",
      "siestaTan": "#E9D8C8",
      "picoEggplant": "#732553",
      "stellarStrawberry": "#FF5C8D",
      "blueWhale": "#1E3442",
      "grauzone": "#85A3B2"
    },
    "background": {
      "primary": "#142030",
      "secondary": "#1E3442",
      "card": "#1E3442",
      "dark": "#0d1620",
      "light": "#E9D8C8",
      "lightAlt": "#f5ece3"
    },
    "text": {
      "primary": "#E9D8C8",
      "secondary": "rgba(233, 216, 200, 0.8)",
      "muted": "rgba(233, 216, 200, 0.6)",
      "inverse": "#142030",
      "dark": "#142030",
      "darkSecondary": "#1E3442"
    },
    "accent": {
      "picoEggplant": "#732553",
      "picoEggplantHover": "#8a2d63",
      "stellarStrawberry": "#FF5C8D",
      "stellarStrawberryLight": "#ff7da6",
      "grauzone": "#85A3B2"
    },
    "status": {
      "success": "#85A3B2",
      "warning": "#E9D8C8",
      "error": "#732553"
    },
    "border": {
      "default": "rgba(233, 216, 200, 0.1)",
      "hover": "rgba(233, 216, 200, 0.2)",
      "dark": "rgba(20, 32, 48, 0.1)"
    }
  },
  "typography": {
    "fonts": {
      "heading": "Playfair Display",
      "body": "Inter",
      "mono": "JetBrains Mono"
    },
    "sizes": {
      "xs": "0.75rem",
      "sm": "0.875rem",
      "base": "1rem",
      "lg": "1.125rem",
      "xl": "1.25rem",
      "2xl": "1.5rem",
      "3xl": "1.875rem",
      "4xl": "2.25rem",
      "5xl": "3rem",
      "6xl": "3.75rem",
      "7xl": "4.5rem",
      "hero": "4.5rem",
      "stat": "3rem"
    },
    "weights": {
      "normal": 400,
      "medium": 500,
      "semibold": 600,
      "bold": 700
    },
    "lineHeights": {
      "none": 1,
      "tight": 1.1,
      "snug": 1.25,
      "normal": 1.5,
      "relaxed": 1.75,
      "loose": 2
    }
  },
  "spacing": {
    "xs": "0.5rem",
    "sm": "1rem",
    "md": "1.5rem",
    "lg": "2rem",
    "xl": "3rem",
    "2xl": "4rem",
    "3xl": "6rem",
    "section": "6rem",
    "card": "2rem"
  },
  "borderRadius": {
    "none": "0",
    "sm": "0.25rem",
    "md": "0.5rem",
    "lg": "1rem",
    "xl": "1.5rem",
    "2xl": "2rem",
    "full": "9999px",
    "card": "1rem"
  },
  "shadows": {
    "sm": "0 1px 2px 0 rgba(20, 32, 48, 0.3)",
    "md": "0 4px 6px -1px rgba(20, 32, 48, 0.4)",
    "lg": "0 10px 15px -3px rgba(20, 32, 48, 0.5)",
    "xl": "0 20px 25px -5px rgba(20, 32, 48, 0.5)",
    "card": "0 4px 6px -1px rgba(20, 32, 48, 0.3)",
    "glow": "0 0 40px rgba(255, 92, 141, 0.3)"
  },
  "components": {
    "card": {
      "background": "#1E3442",
      "borderRadius": "1rem",
      "border": "1px solid rgba(233, 216, 200, 0.1)",
      "shadow": "0 4px 6px -1px rgba(20, 32, 48, 0.3)",
      "padding": "2rem"
    },
    "button": {
      "primary": {
        "background": "#FF5C8D",
        "text": "#142030",
        "borderRadius": "0.5rem",
        "paddingX": "1.5rem",
        "paddingY": "0.75rem"
      },
      "secondary": {
        "background": "transparent",
        "text": "#E9D8C8",
        "border": "1px solid rgba(233, 216, 200, 0.3)",
        "borderRadius": "0.5rem",
        "paddingX": "1.5rem",
        "paddingY": "0.75rem"
      },
      "accent": {
        "background": "#732553",
        "text": "#E9D8C8",
        "borderRadius": "0.5rem",
        "paddingX": "1.5rem",
        "paddingY": "0.75rem"
      }
    },
    "stat": {
      "font": "JetBrains Mono",
      "size": "3rem",
      "color": "#FF5C8D",
      "weight": 700
    }
  }
}
